ds_ctcdecoder/__init__.py
ds_ctcdecoder/_swigwrapper.cpython-39-darwin.so
ds_ctcdecoder/swigwrapper.py
ds_ctcdecoder_m1-0.9.3.dist-info/COPYING
ds_ctcdecoder_m1-0.9.3.dist-info/LICENSE.paddlepaddle
ds_ctcdecoder_m1-0.9.3.dist-info/LICENSE.parlance
ds_ctcdecoder_m1-0.9.3.dist-info/METADATA
ds_ctcdecoder_m1-0.9.3.dist-info/WHEEL
ds_ctcdecoder_m1-0.9.3.dist-info/top_level.txt
ds_ctcdecoder_m1-0.9.3.dist-info/RECORD
